struct_strm/__init__.py
struct_strm/_version.py
struct_strm/compat.py
struct_strm/llm_clients.py
struct_strm/llm_response_handler.py
struct_strm/llm_wrappers.py
struct_strm/partial_parser.py
struct_strm/template.py
struct_strm/tree_queries.py
struct_strm/ui_components.py
struct_strm/structs/dropdown_structs.py
struct_strm/structs/form_structs.py
struct_strm/structs/list_structs.py
struct_strm/structs/rubric_structs.py
struct_strm/structs/switch_structs.py
struct_strm/structs/table_structs.py
struct_strm/templates/example_config.yaml
struct_strm/templates/dropdown/dropdown_complete.html
struct_strm/templates/dropdown/dropdown_container.html
struct_strm/templates/dropdown/dropdown_partial.html
struct_strm/templates/dropdown/dropdown_placeholder.html
struct_strm/templates/form/form_complete.html
struct_strm/templates/form/form_container.html
struct_strm/templates/form/form_partial.html
struct_strm/templates/form/form_placeholder.html
struct_strm/templates/list/list_complete.html
struct_strm/templates/list/list_container.html
struct_strm/templates/list/list_partial.html
struct_strm/templates/list/list_placeholder.html
struct_strm/templates/rubric/rubric_complete.html
struct_strm/templates/rubric/rubric_container.html
struct_strm/templates/rubric/rubric_partial.html
struct_strm/templates/rubric/rubric_partial_outline.html
struct_strm/templates/rubric/rubric_placeholder.html
struct_strm/templates/switch/switch_complete.html
struct_strm/templates/switch/switch_container.html
struct_strm/templates/switch/switch_partial.html
struct_strm/templates/switch/switch_placeholder.html
struct_strm/templates/table/table_complete.html
struct_strm/templates/table/table_container.html
struct_strm/templates/table/table_partial.html
struct_strm/templates/table/table_placeholder.html
struct_strm-0.0.14.dist-info/METADATA
struct_strm-0.0.14.dist-info/WHEEL
struct_strm-0.0.14.dist-info/licenses/LICENSE
struct_strm-0.0.14.dist-info/RECORD
