Metadata-Version: 2.4
Name: struct_strm
Version: 0.0.14
Summary: Stream partial json generated by LLMs into valid json responses
Project-URL: Homepage, https://prestonblackburn.github.io/structured_streamer/
Project-URL: Documentation, https://prestonblackburn.github.io/structured_streamer/
Project-URL: Issues, https://github.com/PrestonBlackburn/structured_streamer/issues
Project-URL: Repository, https://github.com/PrestonBlackburn/structured_streamer
Author-email: Preston Blackburn <prestonblckbrn@gmail.com>
License-Expression: MIT
License-File: LICENSE
Keywords: htmx,json,llm,streaming,web components
Classifier: Development Status :: 3 - Alpha
Classifier: Operating System :: OS Independent
Classifier: Programming Language :: Python
Classifier: Programming Language :: Python :: 3.10
Classifier: Programming Language :: Python :: 3.11
Classifier: Programming Language :: Python :: 3.12
Classifier: Programming Language :: Python :: 3.13
Classifier: Programming Language :: Python :: Implementation :: CPython
Requires-Python: >=3.10
Requires-Dist: tree-sitter-json
Requires-Dist: tree-sitter>=0.25
Provides-Extra: benchmark
Requires-Dist: matplotlib; extra == 'benchmark'
Requires-Dist: pandas; extra == 'benchmark'
Provides-Extra: dev
Requires-Dist: black; extra == 'dev'
Requires-Dist: fastapi; extra == 'dev'
Requires-Dist: jinja2; extra == 'dev'
Requires-Dist: openai; extra == 'dev'
Requires-Dist: pydantic; extra == 'dev'
Requires-Dist: pyright; extra == 'dev'
Requires-Dist: pytest; extra == 'dev'
Requires-Dist: pytest-asyncio; extra == 'dev'
Requires-Dist: pytest-cov[all]; extra == 'dev'
Requires-Dist: pytest-playwright; extra == 'dev'
Requires-Dist: python-multipart; extra == 'dev'
Requires-Dist: python-on-whales; extra == 'dev'
Requires-Dist: requests; extra == 'dev'
Requires-Dist: sse-starlette; extra == 'dev'
Requires-Dist: uvicorn; extra == 'dev'
Provides-Extra: docs
Requires-Dist: mkdocs; extra == 'docs'
Requires-Dist: mkdocs-material; extra == 'docs'
Requires-Dist: mkdocs-techdocs-core; extra == 'docs'
Provides-Extra: hf
Requires-Dist: numpy; extra == 'hf'
Requires-Dist: torch[cpu]; extra == 'hf'
Requires-Dist: transformers; extra == 'hf'
Requires-Dist: xgrammar; extra == 'hf'
Provides-Extra: openai
Requires-Dist: openai; extra == 'openai'
Provides-Extra: pydantic
Requires-Dist: pydantic; extra == 'pydantic'
